[
    {  "id": 1,
       "img":"../imgs/Manta-1.jpeg",
       "nombre":"Manta Ana",
       "descripcion":"Mantas 100% algodón confeccionada a mano en diferentes variantes y colores con terminación al crochet",
       "medidas":"1.20 x 1.80",
       "otros":"Lavar con jabon neutro, centrifugarlo, secado a la sombra.",
       "precio":"€79"
    },
    {  "id": 2,
      "img":"../imgs/Manta-2.jpeg",
      "nombre":"Manta Ana",
      "descripcion":"Mantas 100% algodón confeccionada a mano en diferentes variantes y colores con terminación al crochet",
      "medidas":"1.20 x 1.80",
      "otros":"Lavar con jabon neutro, centrifugarlo, secado a la sombra.",
      "precio":"SIN STOCK"
    },
    { "id": 3,
      "img":"../imgs/Manta-3.jpeg",
      "nombre":"Manta Ana",
      "descripcion":"Mantas 100% algodón confeccionada a mano en diferentes variantes y colores con terminación al crochet",
      "medidas":"1.20 x 1.80",
      "otros":"Lavar con jabon neutro, centrifugarlo, secado a la sombra.",
      "precio":"€79"
    },
    { "id": 4,
      "img":"../imgs/Manta7.jpg",
      "nombre":"Mantas rayas desigual",
      "descripcion":"Mantas 100% algodón con rayas desigual",
      "medidas":"1.20 x 1.80",
      "otros":"Lavar con jabon neutro, centrifugarlo, secado a la sombra.",
      "precio":"€79"
       
    },
    { "id": 5,
      "img":"../imgs/Manta-5.jpeg",
      "nombre":"Manta Ana",
      "descripcion":"Mantas 100% algodón confeccionada a mano en diferentes variantes y colores con terminación al crochet",
      "medidas":"1.20 x 1.80",
      "otros":"Lavar con jabon neutro, centrifugarlo, secado a la sombra.",
      "precio":"€79"
     },
     {
       "id": 6,
       "img":"../imgs/Manta-6.jpeg",
       "nombre":"Manta Ana",
       "descripcion":"Mantas 100% algodón confeccionada a mano en diferentes variantes y colores con terminación al crochet",
       "medidas":"1.20 x 1.80",
       "otros":"Lavar con jabon neutro, centrifugarlo, secado a la sombra.",
       "precio":"SIN STOCK"
     },
      {
      "id": 6,
      "img":"../imgs/Manta8.jpg",
      "nombre":"Mantas rayas desigual",
      "descripcion":"Mantas 100% algodón con rayas desigual  ",
      "medidas":"1.20 x 1.80",
      "otros":"Lavar con jabon neutro, centrifugarlo, secado a la sombra.",
      "precio":"€79"
    }
  
  

   

  
 ]
